{
  "file-explorer:open": [],
  "app:delete-file": [
    {
      "modifiers": [
        "Mod"
      ],
      "key": "Backspace"
    }
  ],
  "markdown:toggle-preview": [
    {
      "modifiers": [
        "Mod"
      ],
      "key": "O"
    }
  ],
  "switcher:open": [
    {
      "modifiers": [
        "Mod"
      ],
      "key": "E"
    }
  ],
  "obsidian-emoji-toolbar:emoji-picker:open-picker": [
    {
      "modifiers": [
        "Alt",
        "Ctrl",
        "Mod"
      ],
      "key": "E"
    }
  ],
  "templater-obsidian:templates/test tem.md": [
    {
      "modifiers": [
        "Alt",
        "Ctrl",
        "Mod"
      ],
      "key": "T"
    }
  ],
  "cm-typewriter-scroll-obsidian:toggle-typewriter-sroll": [
    {
      "modifiers": [
        "Alt",
        "Ctrl",
        "Mod",
        "Shift"
      ],
      "key": "`"
    }
  ],
  "obsidian-to-anki-plugin:anki-scan-vault": [
    {
      "modifiers": [
        "Alt",
        "Shift"
      ],
      "key": "A"
    }
  ]
}